{
	"display": {
		"icon": {
			"id": "minecraft:diamond_sword"
		},
		"title": "Kill or be Killed",
		"description": "Defeat 25,000 mobs",
		"frame": "challenge"
	},
	"parent": "casa:cales.casa/bloodthirsty",
	"criteria": {
		"trigger": {
			"trigger": "minecraft:location",
			"conditions": {
				"player":  {
					"type_specific": {
						"type": "player",
						"stats": [{
                            "type": "minecraft:custom",
                            "stat": "minecraft:mob_kills",
                            "value": {
                                "min": 25000
                            }
                        }]
					}
				}
			}
		}
	}
}